bin/operator_test
bin/subjective_logic_test
include/subjective_logic_lib/util.hpp
include/subjective_logic_lib/multi_source/conflict_operators.hpp
include/subjective_logic_lib/multi_source/fusion_operators.hpp
include/subjective_logic_lib/multi_source/trust_revision_operators.hpp
include/subjective_logic_lib/multi_source/trusted_fusion_operators.hpp
include/subjective_logic_lib/opinions/opinion.hpp
include/subjective_logic_lib/opinions/opinion_no_base.hpp
include/subjective_logic_lib/opinions/trusted_opinion.hpp
include/subjective_logic_lib/types/convert.hpp
include/subjective_logic_lib/types/cuda_compatible_array.hpp
include/subjective_logic_lib/types/cuda_compatible_iterator.hpp
include/subjective_logic_lib/types/dirichlet_distribution.hpp
lib/cmake/subjective_logic_lib/subjective_logic_libConfig.cmake
lib/cmake/subjective_logic_lib/subjective_logic_libConfigVersion.cmake
lib/cmake/subjective_logic_lib/subjective_logic_libTargets-release.cmake
lib/cmake/subjective_logic_lib/subjective_logic_libTargets.cmake
lib/python3.12/site-packages/subjective_logic/__init__.py
lib/python3.12/site-packages/subjective_logic/_subjective_logic_lib_python_api.cpython-312-x86_64-linux-gnu.so
lib/python3.12/site-packages/subjective_logic/_subjective_logic_lib_python_api.pyi
lib/python3.12/site-packages/subjective_logic/draw_sl_opinions.py
lib/python3.12/site-packages/subjective_logic/instance_generator.py
lib/python3.12/site-packages/subjective_logic/trusted_opinion.py
eslimpp-0.1.1.dist-info/METADATA
eslimpp-0.1.1.dist-info/WHEEL
eslimpp-0.1.1.dist-info/RECORD
eslimpp-0.1.1.dist-info/licenses/LICENSE
eslimpp-0.1.1.dist-info/licenses/LICENSES.yaml
