Metadata-Version: 2.4
Name: eslimpp
Version: 0.1.1
Summary: efficient Subjective Logic IMplementation in C++ providing Python interfaces
Author-Email: Thomas Wodtko <wodtko+eslimpp@gmail.com>
License-Expression: Apache-2.0
Project-URL: Homepage, https://github.com/uulm-mrm/eslim
Requires-Python: >=3.8
Requires-Dist: numpy>=1.26.0
Requires-Dist: matplotlib>=2.6.0
